pysvgview/__init__.py
pysvgview/configs.py
pysvgview/main.py
pysvgview/static.py
pysvgview/svg_view.py
pysvgview-0.0.5.dist-info/LICENSE
pysvgview-0.0.5.dist-info/METADATA
pysvgview-0.0.5.dist-info/WHEEL
pysvgview-0.0.5.dist-info/entry_points.txt
pysvgview-0.0.5.dist-info/top_level.txt
pysvgview-0.0.5.dist-info/RECORD
