Metadata-Version: 2.1
Name: pysvgview
Version: 0.0.5
Summary: pysvgview is an SVG viewer
Home-page: https://veltzer.github.io/pysvgview
Download-URL: https://github.com/veltzer/pysvgview
Author: Mark Veltzer
Author-email: mark.veltzer@gmail.com
Maintainer: Mark Veltzer
Maintainer-email: mark.veltzer@gmail.com
License: MIT
Keywords: svg,view,qt
Platform: python3
Classifier: Development Status :: 4 - Beta
Classifier: Environment :: Console
Classifier: Operating System :: OS Independent
Classifier: Programming Language :: Python
Classifier: Programming Language :: Python :: 3
Classifier: Programming Language :: Python :: 3 :: Only
Classifier: Programming Language :: Python :: 3.11
Classifier: Topic :: Utilities
Classifier: License :: OSI Approved :: MIT License
License-File: LICENSE
Requires-Dist: PyQt6
Requires-Dist: PySide6
Requires-Dist: pytconf
Requires-Dist: pylogconf
